marqeta_client/__init__.py
marqeta_client/api/__init__.py
marqeta_client/api/accepted_countries_api.py
marqeta_client/api/account_holder_groups_api.py
marqeta_client/api/auth_controls_api.py
marqeta_client/api/auto_reloads_api.py
marqeta_client/api/bank_transfers_api.py
marqeta_client/api/bulk_issuances_api.py
marqeta_client/api/business_transitions_api.py
marqeta_client/api/businesses_api.py
marqeta_client/api/card_products_api.py
marqeta_client/api/card_transitions_api.py
marqeta_client/api/cardholder_balances_api.py
marqeta_client/api/cards_api.py
marqeta_client/api/chargebacks_api.py
marqeta_client/api/commando_modes_api.py
marqeta_client/api/digital_wallet_provision_requests_api.py
marqeta_client/api/digital_wallet_token_transitions_api.py
marqeta_client/api/digital_wallet_tokens_api.py
marqeta_client/api/direct_deposit_accounts_api.py
marqeta_client/api/direct_deposits_api.py
marqeta_client/api/fee_transfers_api.py
marqeta_client/api/fees_api.py
marqeta_client/api/funding_sources_api.py
marqeta_client/api/gpa_orders_api.py
marqeta_client/api/kyc_api.py
marqeta_client/api/mcc_groups_api.py
marqeta_client/api/merchantgroups_api.py
marqeta_client/api/peer_transfers_api.py
marqeta_client/api/ping_api.py
marqeta_client/api/pins_api.py
marqeta_client/api/program_reserve_api.py
marqeta_client/api/program_transfers_api.py
marqeta_client/api/push_to_card_api.py
marqeta_client/api/real_time_fee_groups_api.py
marqeta_client/api/simulate_api.py
marqeta_client/api/transactions_api.py
marqeta_client/api/user_transitions_api.py
marqeta_client/api/users_api.py
marqeta_client/api/velocity_controls_api.py
marqeta_client/api/web_push_provisioning_api.py
marqeta_client/api/webhooks_api.py
marqeta_client/api_client.py
marqeta_client/configuration.py
marqeta_client/exceptions.py
marqeta_client/models/__init__.py
marqeta_client/models/accepted_countries_list_response.py
marqeta_client/models/accepted_countries_model.py
marqeta_client/models/accepted_countries_update_model.py
marqeta_client-3.0.0.dist-info/METADATA
marqeta_client-3.0.0.dist-info/WHEEL
marqeta_client-3.0.0.dist-info/RECORD
