Metadata-Version: 2.1
Name: marqeta-client
Version: 3.0.0
Summary: Marqeta Core API
Home-page: https://github.com/marqeta-client/SwadeshInc
License: NoLicense
Keywords: OpenAPI,OpenAPI-Generator,Marqeta Core API
Author: OpenAPI Generator Community
Author-email: dev@swadesh.co
Requires-Python: >=3.7,<4.0
Classifier: License :: Other/Proprietary License
Classifier: Programming Language :: Python :: 3
Classifier: Programming Language :: Python :: 3.7
Classifier: Programming Language :: Python :: 3.8
Classifier: Programming Language :: Python :: 3.9
Classifier: Programming Language :: Python :: 3.10
Classifier: Programming Language :: Python :: 3.11
Requires-Dist: aenum (>=3.1.11)
Requires-Dist: pydantic (>=1.10.5,<2.0.0)
Requires-Dist: python-dateutil (>=2.8.2)
Requires-Dist: urllib3 (>=1.25.3)
Project-URL: Repository, https://github.com/marqeta-client/SwadeshInc
